DESCRIPTION.rst
LICENSE
MANIFEST.in
README.rst
setup.py
spotlib/__init__.py
spotlib/_version.py
spotlib/about.py
spotlib/cli.py
spotlib/common.py
spotlib/defaults.py
spotlib/help_menu.py
spotlib/lambda_utils.py
spotlib/statics.py
spotlib/variables.py
spotlib/core/__init__.py
spotlib/core/ancillary.py
spotlib/core/endpoints.py
spotlib/core/spotcore.py
spotlib/core/utc.py